cohesionlm/__init__.py
cohesionlm/py.typed
cohesionlm-0.1.0.dist-info/METADATA
cohesionlm-0.1.0.dist-info/WHEEL
cohesionlm-0.1.0.dist-info/entry_points.txt
cohesionlm-0.1.0.dist-info/RECORD
