Metadata-Version: 2.4
Name: cohesionlm
Version: 0.1.0
Summary: Add your description here
Author-email: Jason Lefever <jason.titus.lefever@gmail.com>
Requires-Python: >=3.12
Requires-Dist: click>=8.1.8
Requires-Dist: numpy>=2.2.1
Requires-Dist: pandas>=2.2.3
